.coveragerc
COPYING
DESCRIPTION.rst
LICENSE.txt
MANIFEST.in
known_broken_constraints.txt
pylintrc
pytest.ini
setup.cfg
setup.py
tox.ini
versioneer.py
ci_support/ensure_sundials_installed.sh
ci_support/install_sundials.sh
dev_hooks/pre-commit.sh
dev_hooks/run_tests.sh
src/disc_solver/__init__.py
src/disc_solver/_version.py
src/disc_solver/_version_.py
src/disc_solver/constants.py
src/disc_solver/float_handling.py
src/disc_solver/logging.py
src/disc_solver/utils.py
src/disc_solver.egg-info/PKG-INFO
src/disc_solver.egg-info/SOURCES.txt
src/disc_solver.egg-info/dependency_links.txt
src/disc_solver.egg-info/entry_points.txt
src/disc_solver.egg-info/requires.txt
src/disc_solver.egg-info/top_level.txt
src/disc_solver/analyse/__init__.py
src/disc_solver/analyse/acc_plot.py
src/disc_solver/analyse/combine_plot.py
src/disc_solver/analyse/compare_plot.py
src/disc_solver/analyse/component_plot.py
src/disc_solver/analyse/conserve_plot.py
src/disc_solver/analyse/derivs_plot.py
src/disc_solver/analyse/diverge_plot.py
src/disc_solver/analyse/hydro_check_plot.py
src/disc_solver/analyse/info.py
src/disc_solver/analyse/j_e_plot.py
src/disc_solver/analyse/params_plot.py
src/disc_solver/analyse/plot.py
src/disc_solver/analyse/taylor_plot.py
src/disc_solver/analyse/utils.py
src/disc_solver/analyse/validate_plot.py
src/disc_solver/file_format/__init__.py
src/disc_solver/file_format/_containers.py
src/disc_solver/file_format/_dumpers.py
src/disc_solver/file_format/_loaders.py
src/disc_solver/file_format/_old_dict_loading.py
src/disc_solver/file_format/_utils.py
src/disc_solver/solve/__init__.py
src/disc_solver/solve/config.py
src/disc_solver/solve/deriv_funcs.py
src/disc_solver/solve/hydrostatic.py
src/disc_solver/solve/j_e_funcs.py
src/disc_solver/solve/mcmc.py
src/disc_solver/solve/mod_hydro.py
src/disc_solver/solve/resolve.py
src/disc_solver/solve/single.py
src/disc_solver/solve/solution.py
src/disc_solver/solve/sonic_root.py
src/disc_solver/solve/stepper.py
src/disc_solver/solve/taylor_space.py
src/disc_solver/solve/utils.py
tests/conftest.py
tests/test_hydrostatic.py
tests/test_mod_hydro.py
tests/test_odes.py
tests/test_odes_sonic.py
tests/test_run.py
tests/test_utils.py
